django_offlinecdn-0.0.11.dist-info/DESCRIPTION.rst
django_offlinecdn-0.0.11.dist-info/METADATA
django_offlinecdn-0.0.11.dist-info/metadata.json
django_offlinecdn-0.0.11.dist-info/RECORD
django_offlinecdn-0.0.11.dist-info/top_level.txt
django_offlinecdn-0.0.11.dist-info/WHEEL
offlinecdn/__init__.py
offlinecdn/exceptions.py
offlinecdn/tests.py
