Metadata-Version: 2.0
Name: django-offlinecdn
Version: 0.0.11
Summary: A nice way to allow for online-offline development, but also use cdn's for package dependencies.
Home-page: https://github.com/gabegaster/django-offlinecdn
Author: Gabe Gaster
Author-email: gabe.gaster@datascopeanalytics.com
License: MIT
Download-URL: https://github.com/gabegaster/django-offlinecdn/archives/master
Platform: UNKNOWN
Classifier: Framework :: Django
Classifier: Intended Audience :: Developers
Classifier: Operating System :: OS Independent
Classifier: Topic :: Software Development
Requires-Dist: Django (==1.8)
Requires-Dist: beautifulsoup4
Requires-Dist: requests
